Workbook

Sheet Capa
B2: GTCON BRASIL CONTABILIDADE
B6: CALCULADORA — IMPACTO DA REFORMA TRIBUTÁRIA NO LUCRO PRESUMIDO E NO SIMPLES NACIONAL
B10: Lucro Presumido (atual x pós-reforma) • Simples Nacional (DAS x Híbrido x Migração)
B13: Cliente: | D13: ='Dados de Entrada'!$C$5 -> Nome do cliente
B14: Setor: | D14: ='Dados de Entrada'!$C$6 -> Comércio/Indústria
B15: Regime atual: | D15: ='Dados de Entrada'!$C$7 -> Lucro Presumido
B16: Ano de análise selecionado: | D16: =Parâmetros!$B$21 -> 2027
B17: Data de referência: | D17: 25/08/2026
B20: Como usar este arquivo: 1. Aba "Parâmetros": confira/ajuste as alíquotas de referência e selecione o ano de análise. 2. Aba "Dados de Entrada": preencha os dados do cliente (Presumido e/ou Simples/PGDAS-D). 3. Aba "Presumido": veja o comparativo de carga tributária atual x pós-reforma. 4. Aba "Simples": compare DAS unificado, Regime Híbrido e migração para o Presumido. 5. Aba "Resumo": visão consolidada com gráficos, pronta para apresentar ao cliente.
B29: Uso interno GTCON Brasil Contabilidade — não distribuir sem revisão técnica

Sheet Parâmetros
A1: PARÂMETROS DA REFORMA TRIBUTÁRIA — CRONOGRAMA E ALÍQUOTAS
A2: LC 214/2025 (regulamenta a EC 132/2023). Alíquotas de referência de CBS e IBS ainda pendentes de fixação definitiva pelo Senado Federal — ajuste as células azuis conforme novas resoluções forem publicadas.
A4: 1. Alíquotas de referência (editável)
A5: CBS — alíquota de referência (vigente a partir de 2027) | B5: 0.088
A6: IBS — alíquota de referência plena (vigente a partir de 2033) | B6: 0.177
A7: Fonte: Secretaria Extraordinária da Reforma Tributária (Min. Fazenda); Resolução CGIBS nº 14/2026 (DOU 31/07/2026). Números sujeitos a revisão anual pelo Comitê Gestor do IBS e pela Receita Federal — reavalie a cada exercício.
A9: 2. Cronograma de transição (LC 214/2025)
A10: Ano | B10: CBS | C10: IBS efetivo | D10: % ICMS/ISS mantido | E10: % IBS aplicado da alíquota plena | F10: Observações
A11: 2026 | B11: =0.009 -> 0.009 | C11: =0.001 -> 0.001 | D11: 1 | E11: 0 | F11: Fase de testes. CBS 0,9% e IBS 0,1% compensáveis com PIS/COFINS e ICMS/ISS devidos — sem aumento de carga (LC 214/2025, arts. 343 e 346).
A12: 2027 | B12: =$B$5 -> 0.088 | C12: =0.001 -> 0.001 | D12: 1 | E12: 0 | F12: CBS plena — PIS e COFINS extintos. IBS segue em alíquota-teste de 0,1% (ainda compensável).
A13: 2028 | B13: =$B$5 -> 0.088 | C13: =0.001 -> 0.001 | D13: 1 | E13: 0 | F13: Último ano antes da transição do IBS. ICMS e ISS seguem integrais.
A14: 2029 | B14: =$B$5 -> 0.088 | C14: =$B$6*0.1 -> 0.0177 | D14: 0.9 | E14: 0.1 | F14: Início da transição: ICMS/ISS reduzidos a 90% da alíquota vigente em 31/12/2028.
A15: 2030 | B15: =$B$5 -> 0.088 | C15: =$B$6*0.2 -> 0.0354 | D15: 0.8 | E15: 0.2 | F15: ICMS/ISS reduzidos a 80% da alíquota-base.
A16: 2031 | B16: =$B$5 -> 0.088 | C16: =$B$6*0.3 -> 0.0531 | D16: 0.7 | E16: 0.3 | F16: ICMS/ISS reduzidos a 70% da alíquota-base.
A17: 2032 | B17: =$B$5 -> 0.088 | C17: =$B$6*0.4 -> 0.0708 | D17: 0.6 | E17: 0.4 | F17: ICMS/ISS reduzidos a 60% da alíquota-base.
A18: 2033 | B18: =$B$5 -> 0.088 | C18: =$B$6 -> 0.177 | D18: 0 | E18: 1 | F18: Transição concluída — ICMS e ISS extintos; IBS e CBS plenos.
A20: 3. Ano de análise selecionado
A21: Ano de análise (selecione) | B21: 2027
A22: CBS do ano selecionado | B22: =INDEX($B$11:$B$18,MATCH($B$21,$A$11:$A$18,0)) -> 0.088
A23: IBS efetivo do ano selecionado | B23: =INDEX($C$11:$C$18,MATCH($B$21,$A$11:$A$18,0)) -> 0.001
A24: % ICMS/ISS ainda mantido no ano selecionado | B24: =INDEX($D$11:$D$18,MATCH($B$21,$A$11:$A$18,0)) -> 1

Sheet Dados de Entrada
A1: DADOS DE ENTRADA — CLIENTE
A2: Preencha apenas as células em azul/amarelo. Os campos do Simples Nacional seguem a nomenclatura do relatório "Discriminação do Recolhimento" do PGDAS-D — copie os valores diretamente do extrato do cliente.
A4: 1. Identificação e regime
B5: Cliente | C5: Nome do cliente
B6: Setor de atuação | C6: Comércio/Indústria
B7: Regime atual do cliente | C7: Lucro Presumido
A8: Dica: preencha a seção 2 (Presumido) sempre — mesmo para clientes do Simples, ela alimenta o cenário "migração" na aba Simples.
A10: 2. Dados para Lucro Presumido
B11: Receita bruta mensal (R$) | C11: 850000
B12: % de compras/insumos sobre a receita (base de créditos de CBS/IBS) | C12: 0.4
B13: Atividade (presunção IRPJ/CSLL) | C13: Comércio/Indústria (8%/12%)
B14: Alíquota ICMS efetiva aplicável (líquida de créditos) (%) | C14: 0.12
B15: Alíquota ISS aplicável (%) | C15: 0.03
B16: Sujeito a IPI? alíquota (%) | C16: 0
A17: Não abordado neste modelo: ICMS-ST/monofásico, incentivos fiscais estaduais e Imposto Seletivo. Trate separadamente para clientes nessas situações.
A19: 3. Dados do Simples Nacional (extraídos do PGDAS-D)
B20: RBT12 (R$) | C20: 9000000
B21: Anexo do Simples Nacional | C21: Anexo I
B22: Fator R (se Anexo III/V) (%) | C22: 0.28
B23: Receita bruta do mês — PGDAS-D (R$) | C23: 750000
B24: Valor total do DAS do mês (R$) — PGDAS-D | C24: 52000
B25: Parcela do DAS ref. ICMS/ISS (R$) | C25: 8500
B26: Parcela do DAS ref. PIS/COFINS (R$) | C26: 2900
B27: % de vendas para clientes B2B (não optantes pelo Simples) (%) | C27: 0.3
B28: % de compras/insumos sobre a receita (base de créditos) (%) | C28: 0.35
A29: Importação do PGDAS-D: o Excel não lê PDF/DOCX diretamente. Copie os valores acima do relatório "Discriminação do Recolhimento" do PGDAS-D do cliente. Se preferir, envie o PDF/DOCX do PGDAS-D em uma conversa com a Claude para pré-preenchimento automático destes campos para um cliente específico.

Sheet Presumido
A1: IMPACTO DA REFORMA TRIBUTÁRIA NO LUCRO PRESUMIDO
A2: ="Setor: "&'Dados de Entrada'!$C$6&" | Ano de análise: "&Parâmetros!$B$21&" | CBS do ano: "&TEXT(Parâmetros!$B$22,"0.00%")&" | IBS efetivo do ano: "&TEXT(Parâmetros!$B$23,"0.00%") -> Setor: Comércio/Indústria | Ano de análise: 2027 | CBS do ano: 8.80% | IBS efetivo do ano: 0.10%
A4: 1. Bases de presunção — IRPJ e CSLL (a reforma não altera IRPJ/CSLL)
A5: % presunção IRPJ (conforme atividade informada) | B5: =IF('Dados de Entrada'!$C$13="Comércio/Indústria (8%/12%)",0.08,IF('Dados de Entrada'!$C$13="Serviços Gerais (32%/32%)",0.32,IF('Dados de Entrada'!$C$13="Serviços — Transporte de carga (8%/12%)",0.08,IF('Dados de Entrada'!$C$13="Serviços — Transporte demais (16%/12%)",0.16,0.08)))) -> 0.08
A6: % presunção CSLL (conforme atividade informada) | B6: =IF('Dados de Entrada'!$C$13="Serviços Gerais (32%/32%)",0.32,0.12) -> 0.12
A8: 2. Comparativo mensal — Regime Atual x Pós-Reforma
A9: Item | B9: Regime Atual | C9: Pós-Reforma (ano selecionado) | D9: Observações
A10: Receita bruta mensal | B10: ='Dados de Entrada'!$C$11 -> 850000 | C10: ='Dados de Entrada'!$C$11 -> 850000
A11: Base de cálculo do IRPJ | B11: =B10*$B$5 -> 68000 | C11: =C10*$B$5 -> 68000
A12: IRPJ (15% + adicional 10% s/ excedente a R$20.000/mês) | B12: =B11*0.15+MAX(0,B11-20000)*0.1 -> 15000 | C12: =C11*0.15+MAX(0,C11-20000)*0.1 -> 15000 | D12: Reforma não altera IRPJ/CSLL — mesma fórmula nas duas colunas.
A13: Base de cálculo da CSLL | B13: =B10*$B$6 -> 102000 | C13: =C10*$B$6 -> 102000
A14: CSLL (9% sobre a base) | B14: =B13*0.09 -> 9180 | C14: =C13*0.09 -> 9180
A15: PIS/COFINS cumulativo (3,65% s/ receita, sem crédito) | B15: =B10*0.0365 -> 31025 | D15: Extinto a partir de 2027 — substituído pela CBS não cumulativa.
A16: CBS líquida (receita × alíq. − créditos s/ compras) | C16: =(C10*Parâmetros!$B$22)-(C10*'Dados de Entrada'!$C$12*Parâmetros!$B$22) -> 44880 | D16: Não cumulativa: desconta crédito sobre o % de compras/insumos informado.
A17: ICMS (regime atual — setor Comércio/Indústria) | B17: =IF('Dados de Entrada'!$C$6="Comércio/Indústria",B10*'Dados de Entrada'!$C$14,0) -> 102000 | C17: =IF('Dados de Entrada'!$C$6="Comércio/Indústria",C10*'Dados de Entrada'!$C$14*Parâmetros!$B$24,0) -> 102000 | D17: Pós-reforma: parcela residual de ICMS ainda vigente no ano selecionado (0% a partir de 2033).
A18: ISS (regime atual — setor Serviços) | B18: =IF('Dados de Entrada'!$C$6="Serviços",B10*'Dados de Entrada'!$C$15,0) -> 0 | C18: =IF('Dados de Entrada'!$C$6="Serviços",C10*'Dados de Entrada'!$C$15*Parâmetros!$B$24,0) -> 0 | D18: Pós-reforma: parcela residual de ISS ainda vigente no ano selecionado (0% a partir de 2033).
A19: IBS líquida (substitui ICMS/ISS — receita × alíq. efetiva − créditos) | C19: =(C10*Parâmetros!$B$23)-(C10*'Dados de Entrada'!$C$12*Parâmetros!$B$23) -> 510 | D19: Não cumulativa e unificada para comércio, indústria e serviços.
A20: IPI | B20: =B10*'Dados de Entrada'!$C$16 -> 0 | C20: =0 -> 0 | D20: Extinto a partir de 2027 (mantido apenas residualmente na Zona Franca de Manaus) — pode surgir Imposto Seletivo para produtos específicos, fora do escopo deste modelo.
A21: TOTAL MENSAL | B21: =B12+B14+B15+B17+B18+B20 -> 157205 | C21: =C12+C14+C16+C17+C18+C19+C20 -> 171570
A22: TOTAL ANUAL (× 12) | B22: =B21*12 -> 1886460 | C22: =C21*12 -> 2058840
A23: Diferença anual — Pós-Reforma vs. Atual (R$) | C23: =C22-B22 -> 172380
A24: Diferença percentual (%) | C24: =IFERROR(C22/B22-1,0) -> 0.091377501
A26: Leitura: um valor negativo em "Diferença" indica REDUÇÃO de carga pós-reforma (efeito dos créditos de CBS/IBS sobre compras/insumos, algo que o PIS/COFINS cumulativo e, no caso do ISS, o regime atual não permitem). Um valor positivo indica AUMENTO de carga — comum em atividades com baixo volume de insumos ou alta margem de valor agregado, onde o crédito recuperável é pequeno em relação à alíquota cheia de CBS/IBS.

Sheet Simples
A1: SIMPLES NACIONAL — DAS UNIFICADO x HÍBRIDO x MIGRAÇÃO PARA LUCRO PRESUMIDO
A2: ="Anexo: "&'Dados de Entrada'!$C$21&" | Ano de análise: "&Parâmetros!$B$21&" | CBS do ano: "&TEXT(Parâmetros!$B$22,"0.00%")&" | IBS efetivo do ano: "&TEXT(Parâmetros!$B$23,"0.00%") -> Anexo: Anexo I | Ano de análise: 2027 | CBS do ano: 8.80% | IBS efetivo do ano: 0.10%
A4: 1. DAS Unificado (regime atual)
A5: Valor do DAS do mês (PGDAS-D) | B5: ='Dados de Entrada'!$C$24 -> 52000
A6: A opção pelo regime unificado mantém a sistemática atual dos Anexos I a V — o próprio DAS já embute internamente as parcelas equivalentes a IBS/CBS durante a transição, sem alteração na carga total do Simples (Resolução CGSN nº 190/2026).
A8: 2. Regime Híbrido (opção a partir de set/2026)
A9: Parcela do DAS mantida (IRPJ + CSLL + CPP) | B9: ='Dados de Entrada'!$C$24-'Dados de Entrada'!$C$25-'Dados de Entrada'!$C$26 -> 40600 | D9: DAS total menos as parcelas de ICMS/ISS e PIS/COFINS (segregadas para fora do DAS).
A10: CBS líquida (fora do DAS, com direito a crédito) | B10: ='Dados de Entrada'!$C$23*Parâmetros!$B$22-'Dados de Entrada'!$C$23*'Dados de Entrada'!$C$28*Parâmetros!$B$22 -> 42900
A11: IBS líquida (fora do DAS, com direito a crédito) | B11: ='Dados de Entrada'!$C$23*Parâmetros!$B$23-'Dados de Entrada'!$C$23*'Dados de Entrada'!$C$28*Parâmetros!$B$23 -> 487.5
A12: Total mensal — Híbrido | B12: =B9+B10+B11 -> 83987.5
A14: 3. Migração para Lucro Presumido
A15: Total mensal estimado — Lucro Presumido pós-reforma | B15: =Presumido!$C$21 -> 171570
A16: Antes de comparar, preencha a seção 2 ("Dados para Lucro Presumido") da aba "Dados de Entrada" com os dados reais deste cliente — receita, % de compras, alíquota de ICMS/ISS e atividade — para que este valor reflita a carga que ele teria como Lucro Presumido.
A18: 4. Comparativo final (mensal e anual)
A19: Cenário | B19: Total mensal | C19: Total anual | D19: Diferença vs. DAS unificado
A20: DAS Unificado | B20: =B5 -> 52000 | C20: =B5*12 -> 624000 | D20: =0 -> 0
A21: Híbrido | B21: =B12 -> 83987.5 | C21: =B12*12 -> 1007850 | D21: =IFERROR(B12/B20-1,0) -> 0.61514423
A22: Migração para Lucro Presumido | B22: =B15 -> 171570 | C22: =B15*12 -> 2058840 | D22: =IFERROR(B15/B20-1,0) -> 2.2994231
A24: Como ler: no Híbrido, IBS e CBS saem do DAS e passam a ser apurados pelas alíquotas cheias do regime regular (não cumulativo) — por isso o valor recolhido costuma SUBIR em relação à parcela pequena que hoje fica embutida no DAS pela tabela do Anexo, especialmente em atividades com baixo % de compras/insumos (typicamente serviços). O ganho não é de caixa: é o crédito INTEGRAL que a empresa passa a destacar na nota para clientes B2B não optantes — algo que o Simples tradicional só permite de forma limitada (proporcional à alíquota efetiva do Anexo). Vale a pena quando o % de vendas B2B informado é alto o suficiente para que esse crédito maior sustente preço ou retenha cliente que, de outra forma, compraria de um concorrente do regime regular. Já a migração para o Lucro Presumido só costuma compensar quando a margem real de lucro é baixa frente à presunção legal, há alto volume de créditos de insumos a recuperar, ou a carteira é majoritariamente B2B — considere também a perda da guia única e o aumento de obrigações acessórias antes de recomendar a migração.

Sheet Resumo
A1: RESUMO COMPARATIVO
A2: ="Cliente: "&'Dados de Entrada'!$C$5&" | Setor: "&'Dados de Entrada'!$C$6&" | Regime atual: "&'Dados de Entrada'!$C$7&" | Ano de análise: "&Parâmetros!$B$21 -> Cliente: Nome do cliente | Setor: Comércio/Indústria | Regime atual: Lucro Presumido | Ano de análise: 2027
A4: 1. Lucro Presumido — Atual x Pós-Reforma (mensal)
A5: Cenário | B5: Total mensal | C5: Total anual | D5: Var. %
A6: Presumido — Regime Atual | B6: =Presumido!$B$21 -> 157205 | C6: =Presumido!$B$22 -> 1886460 | D6: =0 -> 0
A7: Presumido — Pós-Reforma | B7: =Presumido!$C$21 -> 171570 | C7: =Presumido!$C$22 -> 2058840 | D7: =IFERROR(B7/B6-1,0) -> 0.091377501
A9: 2. Simples Nacional — DAS x Híbrido x Migração (mensal)
A10: Cenário | B10: Total mensal | C10: Total anual | D10: Var. % vs. DAS
A11: DAS Unificado | B11: =Simples!$B$20 -> 52000 | C11: =Simples!$C$20 -> 624000 | D11: =0 -> 0
A12: Híbrido | B12: =Simples!$B$21 -> 83987.5 | C12: =Simples!$C$21 -> 1007850 | D12: =Simples!$D$21 -> 0.61514423
A13: Migração para Lucro Presumido | B13: =Simples!$B$22 -> 171570 | C13: =Simples!$C$22 -> 2058840 | D13: =Simples!$D$22 -> 2.2994231
A15: Os valores desta aba são calculados automaticamente a partir das abas "Presumido" e "Simples" — não edite aqui. Para alterar premissas, ajuste as células azuis nas abas "Parâmetros" e "Dados de Entrada".

Sheet Notas e Fontes
A1: NOTAS METODOLÓGICAS E FONTES
A3: 1. Escopo do modelo
A4: • Este arquivo estima o impacto da Reforma Tributária (EC 132/2023 e LC 214/2025) sobre empresas do Lucro Presumido, e compara, para empresas do Simples Nacional, as três alternativas disponíveis a partir de 2026/2027: manter o DAS unificado, optar pelo Regime Híbrido (IBS/CBS apurados por fora, pelo regime regular), ou migrar para o Lucro Presumido.
A5: • Não estão contemplados neste modelo: ICMS-ST/monofásico, Imposto Seletivo, incentivos fiscais estaduais específicos, split payment e cashback, regimes específicos (combustíveis, serviços financeiros, planos de saúde etc.) e o efeito de créditos acumulados de ICMS na transição. Trate esses pontos caso a caso.
A7: 2. Alíquotas e cronograma
A8: • 2026: alíquotas-teste de CBS (0,9%) e IBS (0,1%) — compensáveis com os tributos atuais, sem aumento de carga (LC 214/2025, arts. 343 e 346).
A9: • 2027-2028: CBS plena (extinção de PIS/COFINS); IBS segue em alíquota-teste de 0,1% (ainda compensável). ICMS e ISS permanecem integrais.
A10: • 2029-2032: transição do ICMS/ISS para o IBS — reduzidos a 90%/80%/70%/60% da alíquota vigente em 31/12/2028, na mesma proporção em que o IBS assume participação crescente (10%/20%/30%/40% da alíquota plena).
A11: • 2033: transição concluída — ICMS e ISS extintos; IBS e CBS plenos.
A12: • Alíquotas de referência utilizadas por padrão neste arquivo: CBS 8,8% e IBS 17,7% (soma ~26,5%, teto legal da LC 214/2025). A Resolução CGIBS nº 14/2026 projetou 27,91% para fins orçamentários do próprio Comitê Gestor — não é a alíquota definitiva. Ajuste as células B5:B6 da aba "Parâmetros" conforme novas resoluções.
A14: 3. Lucro Presumido
A15: • IRPJ e CSLL não são alterados pela reforma — mesma sistemática de presunção (8%/12% comércio-indústria, 32%/32% serviços gerais, conforme atividade) e adicional de 10% de IRPJ sobre o que exceder R$20.000/mês.
... A32: Documento de apoio interno GTCON Brasil Contabilidade. Última atualização: 25/08/2026. Revisar sempre que novas resoluções do CGSN, CGIBS ou do Senado Federal forem publicadas.
